crypto_pandas/__init__.py
crypto_pandas/ccxt/__init__.py
crypto_pandas/ccxt/async_ccxt_pandas_exchange.py
crypto_pandas/ccxt/base_processor.py
crypto_pandas/ccxt/ccxt_pandas_exchange.py
crypto_pandas/ccxt/method_mappings.py
crypto_pandas/ccxt/order_schema.py
crypto_pandas/utils/__init__.py
crypto_pandas/utils/_generate_typed_interface.py
crypto_pandas/utils/async_ccxt_pandas_exchange_typed.py
crypto_pandas/utils/ccxt_pandas_exchange_typed.py
crypto_pandas/utils/pandas_utils.py
crypto_pandas/utils/utils.py
crypto_pandas-0.12.7.dist-info/licenses/LICENSE
crypto_pandas-0.12.7.dist-info/METADATA
crypto_pandas-0.12.7.dist-info/WHEEL
crypto_pandas-0.12.7.dist-info/RECORD
