Metadata-Version: 2.4
Name: crypto-pandas
Version: 0.12.7
Summary: Library combining the power of CCXT with Pandas.
License-Expression: Apache-2.0
License-File: LICENSE
Author: Sigma Quantiphi
Author-email: contact@sqphi.com
Requires-Python: >=3.11
Classifier: Programming Language :: Python :: 3
Classifier: Programming Language :: Python :: 3.11
Classifier: Programming Language :: Python :: 3.12
Classifier: Programming Language :: Python :: 3.13
Classifier: Programming Language :: Python :: 3.14
Requires-Dist: async-lru (>=2.0.0,<3.0.0)
Requires-Dist: cachetools (>=6.0.0,<7.0.0)
Requires-Dist: ccxt (>=4.5.0,<5.0.0)
Requires-Dist: orjson (>=3.0.0,<4.0.0)
Requires-Dist: pandas[computation,output-formatting,performance] (>=2.2.3,<3.0.0)
Requires-Dist: pandera (>=0.22.1,<0.27.0)
Project-URL: Documentation, https://github.com/sigma-quantiphi/crypto-pandas
Project-URL: Homepage, https://github.com/sigma-quantiphi/crypto-pandas
Project-URL: Repository, https://github.com/sigma-quantiphi/crypto-pandas
